java_gc/__init__.py
java_gc-0.2.0.dist-info/DESCRIPTION.rst
java_gc-0.2.0.dist-info/METADATA
java_gc-0.2.0.dist-info/RECORD
java_gc-0.2.0.dist-info/WHEEL
java_gc-0.2.0.dist-info/entry_points.txt
java_gc-0.2.0.dist-info/metadata.json
java_gc-0.2.0.dist-info/top_level.txt
