Metadata-Version: 2.0
Name: java-gc
Version: 0.2.0
Summary: Trigger a full Java garbage collection
Home-page: https://github.com/mmmorris1975/java-gc
Author: Michael Morris
Author-email: mmmorris1975@netscape.net
License: MIT
Keywords: java gc jcmd
Platform: UNKNOWN
Classifier: Development Status :: 4 - Beta
Classifier: Intended Audience :: Developers
Classifier: Intended Audience :: System Administrators
Classifier: License :: OSI Approved :: MIT License
Classifier: Programming Language :: Python :: 2.7
Classifier: Programming Language :: Python :: 3
Requires-Python: >=2.7, <4
